messenger/Messenger.py
messenger/__init__.py
amqpymessenger-0.1.0.dist-info/METADATA
amqpymessenger-0.1.0.dist-info/WHEEL
amqpymessenger-0.1.0.dist-info/top_level.txt
amqpymessenger-0.1.0.dist-info/RECORD
