Metadata-Version: 2.1
Name: amqpymessenger
Version: 0.1.0
Summary: AMQP library for python
Home-page: https://github.com/yeranosyanvahan/messenger
Author: Vahan Yeranosyan
Author-email: vahan@yeranosyanvahan.com
Maintainer: Vahan Yeranosyan
Maintainer-email: vahan@yeranosyanvahan.com
License: MIT
Classifier: Development Status :: 2 - Pre-Alpha
Classifier: Intended Audience :: Developers
Requires-Dist: pika
